brad_nlp_helpers/__init__.py
brad_nlp_helpers/nlp.py
brad_nlp_helpers-0.1.1.dist-info/DESCRIPTION.rst
brad_nlp_helpers-0.1.1.dist-info/METADATA
brad_nlp_helpers-0.1.1.dist-info/RECORD
brad_nlp_helpers-0.1.1.dist-info/WHEEL
brad_nlp_helpers-0.1.1.dist-info/metadata.json
brad_nlp_helpers-0.1.1.dist-info/top_level.txt
