Metadata-Version: 2.0
Name: brad-nlp-helpers
Version: 0.1.1
Summary: Python based packages for NLP EDA
Home-page: https://github.com/bradaallen/nlp_helper
Author: Brad Allen
Author-email: bradaallen@gmail.com
License: MIT
Platform: UNKNOWN
Requires-Dist: collections
Requires-Dist: nltk
Requires-Dist: pandas
